pipen_annotate/__init__.py
pipen_annotate/annotate.py
pipen_annotate/sections.py
pipen_annotate/utils.py
pipen_annotate-1.0.1.dist-info/METADATA
pipen_annotate-1.0.1.dist-info/WHEEL
pipen_annotate-1.0.1.dist-info/licenses/LICENSE
pipen_annotate-1.0.1.dist-info/RECORD
